skmiscpy/__init__.py
skmiscpy/cbs.py
skmiscpy/plotting.py
skmiscpy/utils.py
skmiscpy-0.4.0.dist-info/LICENSE
skmiscpy-0.4.0.dist-info/METADATA
skmiscpy-0.4.0.dist-info/WHEEL
skmiscpy-0.4.0.dist-info/RECORD
