Metadata-Version: 2.1
Name: skmiscpy
Version: 0.4.0
Summary: Contains a few functions useful for data-analysis, causal inference etc.
License: MIT
Author: Shafayet Khan Shafee
Requires-Python: >=3.9,<4.0
Classifier: License :: OSI Approved :: MIT License
Classifier: Programming Language :: Python :: 3
Classifier: Programming Language :: Python :: 3.9
Classifier: Programming Language :: Python :: 3.10
Classifier: Programming Language :: Python :: 3.11
Classifier: Programming Language :: Python :: 3.12
Requires-Dist: matplotlib (>=3.9.1.post1,<4.0.0)
Requires-Dist: numpy (>=2.0.1,<3.0.0)
Requires-Dist: pandas (>=2.2.2,<3.0.0)
Requires-Dist: seaborn (>=0.13.2,<0.14.0)
